tox_envlist-0.3.0.dist-info/WHEEL
tox_envlist-0.3.0.dist-info/entry_points.txt
tox_envlist-0.3.0.dist-info/METADATA
tox_envlist-0.3.0.dist-info/top_level.txt
tox_envlist-0.3.0.dist-info/LICENSE
tox_envlist/py.typed
tox_envlist/__init__.py
tox_envlist-0.3.0.dist-info/RECORD
