Metadata-Version: 2.1
Name: tox-envlist
Version: 0.3.0
Summary: Allows selection of a different tox envlist.
Author-email: Dominic Davis-Foster <dominic@davis-foster.co.uk>
License: MIT
Keywords: tox,tox-plugin
Home-page: https://github.com/python-coincidence/tox-envlist
Project-URL: Issue Tracker, https://github.com/python-coincidence/tox-envlist/issues
Project-URL: Source Code, https://github.com/python-coincidence/tox-envlist
Platform: Windows
Platform: macOS
Platform: Linux
Classifier: Development Status :: 4 - Beta
Classifier: Framework :: tox
Classifier: Intended Audience :: Developers
Classifier: License :: OSI Approved :: MIT License
Classifier: Operating System :: OS Independent
Classifier: Programming Language :: Python
Classifier: Programming Language :: Python :: 3 :: Only
Classifier: Programming Language :: Python :: 3.7
Classifier: Programming Language :: Python :: 3.8
Classifier: Programming Language :: Python :: 3.9
Classifier: Programming Language :: Python :: Implementation :: CPython
Classifier: Topic :: Software Development :: Quality Assurance
Classifier: Topic :: Software Development :: Testing
Classifier: Topic :: Software Development :: Testing :: Unit
Classifier: Typing :: Typed
Requires-Python: >=3.7
Requires-Dist: braceexpand>=0.1.6
Requires-Dist: domdf-python-tools>=2.8.1
Requires-Dist: pluggy>=0.13.1
Requires-Dist: tox>=3.18.0
